{
  "2024-10-29": {
    "name": "Neuro solo stream",
    "description": "scary neuro aaaaaaaaaa",
    "customBuckets": {
      "neuro": "streams/solo/neuro.json"
    },
    "weights": {
      "neuro": 21,
      "chat": 3
    },
    "boardWidth": 5,
    "boardHeight": 5,
    "multipleFreeSpacesBehaviour": "random",
    "freeSpaces": [
      {
        "pos": [2, 2],
        "src": "/assets/artworks/neuro_witch_hat.jpg",
        "alt": "Neuro-sama in her halloween (witch) outfit, under the night sky",
        "credit": {
          "name": "ame.000_57340",
          "source": "https://discord.com/channels/574720535888396288/1289261175611068459/1289261175611068459"
        }
      },
      {
        "pos": [2, 2],
        "src": "/assets/artworks/neuro_autumn_wink.png",
        "alt": "Neuro-sama wearing a yellow top and a hoodie which resembles her usual outfit, with said hoodie partially off. Neuro-sama is winking at the viewer.",
        "credit": {
          "name": "hanashi1821 (commissioner: soul1419)",
          "source": "https://discord.com/channels/574720535888396288/1299375399557398650/1299375399557398650"
        }
      }
    ]
  }
}
